ratr0/util/__init__.py
ratr0/util/compile_clist.py
ratr0/util/compute_lf.py
ratr0/util/file_info.py
ratr0/util/levels.py
ratr0/util/png_util.py
ratr0/util/sprites.py
ratr0/util/tiled.py
ratr0/util/tiles.py
ratr0_utils-0.2.2.data/scripts/ratr0-converttiled
ratr0_utils-0.2.2.data/scripts/ratr0-file
ratr0_utils-0.2.2.data/scripts/ratr0-makecoplist
ratr0_utils-0.2.2.data/scripts/ratr0-makelevel
ratr0_utils-0.2.2.data/scripts/ratr0-makeplanes
ratr0_utils-0.2.2.data/scripts/ratr0-makesprites
ratr0_utils-0.2.2.data/scripts/ratr0-maketiles
ratr0_utils-0.2.2.data/scripts/ratr0-wav2raw8
ratr0_utils-0.2.2.dist-info/LICENSE
ratr0_utils-0.2.2.dist-info/METADATA
ratr0_utils-0.2.2.dist-info/WHEEL
ratr0_utils-0.2.2.dist-info/top_level.txt
ratr0_utils-0.2.2.dist-info/RECORD
