Metadata-Version: 2.1
Name: ratr0_utils
Version: 0.2.2
Summary: ratr0-utils is a collection of utilities for game development using the RATR0 engine
Home-page: https://github.com/weiju/ratr0-utils
Author: Wei-ju Wu
Author-email: weiju.wu@gmail.com
Maintainer: Wei-ju Wu
Maintainer-email: weiju.wu@gmail.com
License: GPL V3
Keywords: ratr0,amiga,game,development,classic,ecs,aga
Classifier: Development Status :: 4 - Beta
Classifier: Environment :: Console
Classifier: Intended Audience :: Developers
Classifier: Natural Language :: English
Classifier: License :: OSI Approved :: GNU General Public License v3 (GPLv3)
Classifier: Operating System :: OS Independent
Classifier: Programming Language :: Python
Classifier: Programming Language :: Python :: 3
Classifier: Programming Language :: Python :: 3.5
Classifier: Programming Language :: Python :: Implementation :: CPython
Classifier: Topic :: Software Development :: Libraries :: Python Modules
License-File: LICENSE
Requires-Dist: pillow
